metrics.py
hfl_metrics-0.0.2.dist-info/METADATA
hfl_metrics-0.0.2.dist-info/WHEEL
hfl_metrics-0.0.2.dist-info/top_level.txt
hfl_metrics-0.0.2.dist-info/RECORD
