Metadata-Version: 2.2
Name: hfl-metrics
Version: 0.0.2
Summary: Send metrics to dedicated endpoint
Requires-Python: >=3.7
Requires-Dist: requests
Requires-Dist: fastapi
